<fsmxml xmlns="http://vaucanson.lrde.epita.fr" version="1.0">
  <automaton>
    <valueType>
      <writingData closePar=")" openPar="(" plusSym="+" spacesSym=" " starSym="*" timesSym="." weightClosing="}" weightOpening="{" zeroSym="0"/>
      <semiring operations="classical" set="B" type="numerical"/>
      <monoid genDescrip="enum" genKind="simple" genSort="letters" type="free">
        <writingData identitySym="1"/>
        <monGen value="a"/>
        <monGen value="b"/>
      </monoid>
    </valueType>
    <automatonStruct>
      <states>
        <state id="s0" name="s0">
          <geometricData x="-265.0" y="147.0"/>
          <drawingData fillColor="#94F7F7" strokeColor="#990066" strokeWidth="2.0"/>
        </state>
        <state id="s1" name="s1">
          <geometricData x="-36.0" y="11.0"/>
          <drawingData fillColor="#94F7F7" strokeColor="#990066" strokeWidth="2.0"/>
        </state>
      </states>
      <transitions>
        <transition source="s0" target="s1">
          <geometricData>
            <controlPoint x="-167.0" y="91.0"/>
          </geometricData>
          <drawingData strokeColor="#6482B9" strokeWidth="2.0" startArrow="none" endArrow="classic"/>
          <label>
            <monElmt>
              <monGen value="a"/>
            </monElmt>
          </label>
        </transition>
      </transitions>
    </automatonStruct>
  </automaton>
</fsmxml>
